scPECA/PECA_network.py
scPECA/__init__.py
scPECA/homer_motifinding.py
scPECA/mf_collect.py
scPECA/mfbs.py
scPECA/preprocessing.py
scPECA/prior_install.py
scPECA/scPECA_main.py
scPECA/utils.py
scPECA/4cellline/4cellline_scATAC.csv
scPECA/4cellline/4cellline_scATAC_meta.csv
scPECA/4cellline/4cellline_scRNA.csv
scPECA/4cellline/4cellline_scRNA_meta.csv
scPECA/4cellline/BJ_PSExp.txt
scPECA/4cellline/GM12878_PSExp.txt
scPECA/4cellline/H1_PSExp.txt
scPECA/4cellline/K562_PSExp.txt
scPECA/Cones/Cones_scATAC.csv
scPECA/Cones/Cones_scRNA.csv
scPECA/Data/CRInfo_human.mat
scPECA/Data/CRInfo_mouse.mat
scPECA/Data/MotifMatch_human_rmdup.mat
scPECA/Data/MotifMatch_mouse_rmdup.mat
scPECA/Data/TFTG_human_nagetriveControl.mat
scPECA/Data/TFTG_mouse_nagetriveControl.mat
scPECA/Data/all_motif_rmdup
scPECA/Data/genome_100k_hg19.bed
scPECA/Data/genome_100k_hg38.bed
scPECA/Data/genome_100k_mm10.bed
scPECA/Data/genome_100k_mm9.bed
scPECA/Data/hg19_gene_length.txt
scPECA/Data/hg38_gene_length.txt
scPECA/Data/mm10_gene_length.txt
scPECA/Data/mm9_gene_length.txt
scPECA-2.0.dist-info/LICENSE
scPECA-2.0.dist-info/METADATA
scPECA-2.0.dist-info/WHEEL
scPECA-2.0.dist-info/top_level.txt
scPECA-2.0.dist-info/RECORD
