Metadata-Version: 2.1
Name: scPECA
Version: 2.0
Summary: PECA2 gene regulatory network construction for single-cell data
Home-page: https://github.com/zhangjiahao1234/scPECA
Author: Jiahao Zhang
Author-email: zhangjiahao@amss.ac.cn
License: UNKNOWN
Platform: UNKNOWN
License-File: LICENSE
